wagtailcloudinary/__init__.py
wagtailcloudinary/admin.py
wagtailcloudinary/api.py
wagtailcloudinary/apps.py
wagtailcloudinary/blocks.py
wagtailcloudinary/fields.py
wagtailcloudinary/models.py
wagtailcloudinary/utils.py
wagtailcloudinary/wagtail_hooks.py
wagtailcloudinary/widgets.py
wagtailcloudinary/management/__init__.py
wagtailcloudinary/management/commands/__init__.py
wagtailcloudinary/management/commands/import_cloudinary_images.py
wagtailcloudinary/migrations/0001_initial.py
wagtailcloudinary/migrations/__init__.py
wagtailcloudinary/static/wagtailcloudinary/css/main.css
wagtailcloudinary/static/wagtailcloudinary/js/cloudinary-chooser-telepath.js
wagtailcloudinary/static/wagtailcloudinary/js/cloudinary-chooser.js
wagtailcloudinary/templates/wagtailcloudinary/chooser/chooser.html
wagtailcloudinary/templates/wagtailcloudinary/chooser/results.html
wagtailcloudinary/templates/wagtailcloudinary/include/cloudinary.html
wagtailcloudinary/templates/wagtailcloudinary/include/pagination_nav.html
wagtailcloudinary/templates/wagtailcloudinary/widgets/cloudinary_chooser.html
wagtailcloudinary/views/__init__.py
wagtailcloudinary/views/chooser.py
wagtailcloudinary-2.3.0.dist-info/METADATA
wagtailcloudinary-2.3.0.dist-info/WHEEL
wagtailcloudinary-2.3.0.dist-info/licenses/LICENSE
wagtailcloudinary-2.3.0.dist-info/RECORD
