Metadata-Version: 2.4
Name: wagtailcloudinary
Version: 2.3.0
Summary: Cloudinary support for Wagtail CMS
Project-URL: Homepage, https://gitlab.com/thelabnyc/wagtailcloudinary
Project-URL: Repository, https://gitlab.com/thelabnyc/wagtailcloudinary
Author-email: thelab <thelabdev@thelab.co>
License: ISC
License-File: LICENSE
Requires-Python: >=3.11
Requires-Dist: cloudinary<1.45,>=1.44.0
Requires-Dist: python-dateutil>=2.9.0.post0
Requires-Dist: wagtail>=6.3
